enc_netzwerkverbindung/__init__.py
enc_netzwerkverbindung/exceptions.py
enc_netzwerkverbindung/_generell/__init__.py
enc_netzwerkverbindung/_generell/cipher.py
enc_netzwerkverbindung/_generell/get_ip.py
enc_netzwerkverbindung/_generell/aes/__init__.py
enc_netzwerkverbindung/_generell/aes/aes_gen.py
enc_netzwerkverbindung/_generell/aes/aes_kodierung.py
enc_netzwerkverbindung/_generell/rsa/__init__.py
enc_netzwerkverbindung/_generell/rsa/rsa_gen.py
enc_netzwerkverbindung/_generell/rsa/rsa_kodierung.py
enc_netzwerkverbindung/_generell/verbindung/__init__.py
enc_netzwerkverbindung/_generell/verbindung/_basis_com.py
enc_netzwerkverbindung/_generell/verbindung/client_verbindung.py
enc_netzwerkverbindung/_generell/verbindung/server_verbindung.py
enc_netzwerkverbindung/client/__client.py
enc_netzwerkverbindung/client/__init__.py
enc_netzwerkverbindung/server/__client_handler.py
enc_netzwerkverbindung/server/__client_info.py
enc_netzwerkverbindung/server/__init__.py
enc_netzwerkverbindung/server/__kontext.py
enc_netzwerkverbindung/server/__server.py
enc_netzwerkverbindung/server/__server_info.py
enc_netzwerkverbindung/server/__uebergabe_sk_pk.py
enc_netzwerkverbindung/server/__verwaltung/__init__.py
enc_netzwerkverbindung/server/__verwaltung/crypto_verwalter.py
enc_netzwerkverbindung/server/__verwaltung/rsa_basis.py
enc_netzwerkverbindung/server/__verwaltung/rsa_verwalter.py
enc_netzwerkverbindung_heureka_code-2.0.0.dist-info/METADATA
enc_netzwerkverbindung_heureka_code-2.0.0.dist-info/WHEEL
enc_netzwerkverbindung_heureka_code-2.0.0.dist-info/top_level.txt
enc_netzwerkverbindung_heureka_code-2.0.0.dist-info/RECORD
