Metadata-Version: 2.1
Name: enc-netzwerkverbindung-heureka-code
Version: 2.0.0
Summary: Einfacher Versuch, eine verschlüsselte Netzwerkverbindung herzustellen
Home-page: https://heureka-code.github.io/Enc-Netzwerkverbindung-heureka-code/
Requires-Python: >=3.9
Requires-Dist: pycryptodome
Provides-Extra: dev
Requires-Dist: commitizen ; extra == 'dev'
Provides-Extra: doc
Requires-Dist: sphinx ; extra == 'doc'
Provides-Extra: test
Requires-Dist: hypothesis ; extra == 'test'
